LICENSE
MANIFEST.in
README.md
setup.py
pagseguro_xml/__init__.py
pagseguro_xml.egg-info/PKG-INFO
pagseguro_xml.egg-info/SOURCES.txt
pagseguro_xml.egg-info/dependency_links.txt
pagseguro_xml.egg-info/not-zip-safe
pagseguro_xml.egg-info/requires.txt
pagseguro_xml.egg-info/top_level.txt
pagseguro_xml/assinatura/__init__.py
pagseguro_xml/assinatura/v2/__init__.py
pagseguro_xml/assinatura/v2/classes/__init__.py
pagseguro_xml/assinatura/v2/classes/cancelamento.py
pagseguro_xml/assinatura/v2/classes/consulta.py
pagseguro_xml/assinatura/v2/classes/erros.py
pagseguro_xml/assinatura/v2/classes/requisicao.py
pagseguro_xml/consultas/__init__.py
pagseguro_xml/consultas/v2/__init__.py
pagseguro_xml/consultas/v2/classes/__init__.py
pagseguro_xml/consultas/v2/classes/abandonadas.py
pagseguro_xml/consultas/v2/classes/detalhes.py
pagseguro_xml/consultas/v2/classes/historico.py
pagseguro_xml/consultas/v3/__init__.py
pagseguro_xml/consultas/v3/classes/__init__.py
pagseguro_xml/consultas/v3/classes/detalhes.py
pagseguro_xml/core/__init__.py
pagseguro_xml/core/base_classes.py
pagseguro_xml/notificacao/__init__.py
pagseguro_xml/notificacao/v3/__init__.py
pagseguro_xml/notificacao/v3/classes/__init__.py
pagseguro_xml/notificacao/v3/classes/transacao.py
pagseguro_xml/pagamento/__init__.py
pagseguro_xml/pagamento/v2/__init__.py
pagseguro_xml/pagamento/v2/classes/__init__.py
pagseguro_xml/pagamento/v2/classes/erros.py
pagseguro_xml/pagamento/v2/classes/pagamento.py
pagseguro_xml/tests/__init__.py
pagseguro_xml/tests/test_classes_assinatura/__init__.py
pagseguro_xml/tests/test_classes_assinatura/test_cancelamento_v2.py
pagseguro_xml/tests/test_classes_assinatura/test_consulta_v2.py
pagseguro_xml/tests/test_classes_assinatura/test_erros_v2.py
pagseguro_xml/tests/test_classes_assinatura/test_requisicao_v2.py
pagseguro_xml/tests/test_classes_consultas/__init__.py
pagseguro_xml/tests/test_classes_consultas/test_abandonadas_v2.py
pagseguro_xml/tests/test_classes_consultas/test_detalhes_v3.py
pagseguro_xml/tests/test_classes_consultas/test_historico_v2.py
pagseguro_xml/tests/test_classes_notificacao/__init__.py
pagseguro_xml/tests/test_classes_notificacao/test_transacao_v3.py
