Metadata-Version: 1.0
Name: pagseguro_xml
Version: 0.0.3.b0
Summary: API PagSeguro v2 e v3 em XML
Home-page: https://github.com/arannasousa/pagseguro_xml
Author: Aranna Sousa Santos
Author-email: asousas@live.com
License: GNU General Public License v2 (GPLv2)
Download-URL: https://github.com/arannasousa/pagseguro_xml/archive/master.zip
Keywords: pagseguro,payment,payments,credit-card,pagseguro_xml,xml,transacao,assinatura
Platform: UNKNOWN
Classifier: Development Status :: 4 - Beta
Classifier: Environment :: Web Environment
Classifier: Intended Audience :: Developers
Classifier: Natural Language :: Portuguese (Brazilian)
Classifier: License :: OSI Approved :: GNU General Public License v2 (GPLv2)
Classifier: Programming Language :: Python
Classifier: Programming Language :: Python :: 2
Classifier: Programming Language :: Python :: 2.6
Classifier: Programming Language :: Python :: 2.7
Classifier: Programming Language :: Python :: 3
Classifier: Programming Language :: Python :: 3.3
